{
	"name": "xmao_Watemark_Dataset",
	"properties": {
		"linkedServiceName": {
			"referenceName": "guyinsql",
			"type": "LinkedServiceReference",
			"parameters": {
				"DBName": {
					"value": "@dataset().DBName",
					"type": "Expression"
				}
			}
		},
		"parameters": {
			"DBName": {
				"type": "string",
				"defaultValue": "Incremental_Demo"
			},
			"SchemaName": {
				"type": "string",
				"defaultValue": "dbo"
			},
			"TableName": {
				"type": "string"
			}
		},
		"folder": {
			"name": "Ford/SCAV+ Training/xmao11"
		},
		"annotations": [],
		"type": "AzureSqlTable",
		"schema": [],
		"typeProperties": {
			"schema": {
				"value": "@dataset().SchemaName",
				"type": "Expression"
			},
			"table": {
				"value": "@dataset().TableName",
				"type": "Expression"
			}
		}
	},
	"type": "Microsoft.DataFactory/factories/datasets"
}